experiment_wrapper/__init__.py
experiment_wrapper/experiment.py
experiment_wrapper/experiment_suite.py
experiment_wrapper/rollout_trajectory.py
experiment_wrapper-1.1.0.dist-info/LICENSE.txt
experiment_wrapper-1.1.0.dist-info/METADATA
experiment_wrapper-1.1.0.dist-info/WHEEL
experiment_wrapper-1.1.0.dist-info/top_level.txt
experiment_wrapper-1.1.0.dist-info/RECORD
